[
  {
    "id": "leather-arms",
    "name": "皮製手套",
    "nameEn": "",
    "setName": "皮製",
    "setNameEn": "Leather",
    "part": "arms",
    "defense": 182,
    "skills": [
      {
        "skillId": "defense-boost",
        "level": 1
      },
      {
        "skillId": "thunder-resistance",
        "level": 1
      }
    ],
    "driftstoneSlots": 1,
    "image": "/images/armor/leather-arms.webp"
  },
  {
    "id": "alloy-arms",
    "name": "合金腕甲",
    "nameEn": "",
    "setName": "合金",
    "setNameEn": "Alloy",
    "part": "arms",
    "defense": 182,
    "skills": [
      {
        "skillId": "health-boost",
        "level": 1
      }
    ],
    "driftstoneSlots": 1,
    "image": "/images/armor/alloy-arms.webp"
  },
  {
    "id": "jagras-arms",
    "name": "凶豺龍腕甲",
    "nameEn": "",
    "setName": "凶豺龍",
    "setNameEn": "Great Jagras",
    "part": "arms",
    "defense": 182,
    "skills": [
      {
        "skillId": "firm-foothold",
        "level": 1
      },
      {
        "skillId": "water-attack",
        "level": 1
      }
    ],
    "driftstoneSlots": 1,
    "image": "/images/armor/jagras-arms.webp"
  },
  {
    "id": "kulu-arms",
    "name": "搔鳥腕甲",
    "nameEn": "",
    "setName": "搔鳥",
    "setNameEn": "Kulu-Ya-Ku",
    "part": "arms",
    "defense": 182,
    "skills": [
      {
        "skillId": "last-stand-guard",
        "level": 1
      },
      {
        "skillId": "critical-eye",
        "level": 1
      }
    ],
    "driftstoneSlots": 1,
    "image": "/images/armor/kulu-arms.webp"
  },
  {
    "id": "pukei-arms",
    "name": "毒妖鳥腕甲",
    "nameEn": "",
    "setName": "毒妖鳥",
    "setNameEn": "Pukei-Pukei",
    "part": "arms",
    "defense": 182,
    "skills": [
      {
        "skillId": "poison-attack",
        "level": 1
      },
      {
        "skillId": "poison-resistance",
        "level": 1
      }
    ],
    "driftstoneSlots": 1,
    "image": "/images/armor/pukei-arms.webp"
  },
  {
    "id": "coral-pukei-arms",
    "name": "妖水腕甲",
    "nameEn": "",
    "setName": "妖水",
    "setNameEn": "Coral Pukei-Pukei",
    "part": "arms",
    "defense": 182,
    "skills": [
      {
        "skillId": "battle-temper",
        "level": 1
      },
      {
        "skillId": "skyward-striker",
        "level": 1
      }
    ],
    "driftstoneSlots": 1,
    "image": "/images/armor/coral-pukei-arms.webp"
  },
  {
    "id": "barroth-arms",
    "name": "土砂龍腕甲",
    "nameEn": "",
    "setName": "土砂龍",
    "setNameEn": "Barroth",
    "part": "arms",
    "defense": 182,
    "skills": [
      {
        "skillId": "guard",
        "level": 1
      }
    ],
    "driftstoneSlots": 1,
    "image": "/images/armor/barroth-arms.webp"
  },
  {
    "id": "girros-arms",
    "name": "凶顎龍腕甲",
    "nameEn": "",
    "setName": "凶顎龍",
    "setNameEn": "Great Girros",
    "part": "arms",
    "defense": 182,
    "skills": [
      {
        "skillId": "sneak-attack",
        "level": 1
      },
      {
        "skillId": "earplugs",
        "level": 1
      }
    ],
    "driftstoneSlots": 1,
    "image": "/images/armor/girros-arms.webp"
  },
  {
    "id": "kadachi-arms",
    "name": "飛雷龍腕甲",
    "nameEn": "",
    "setName": "飛雷龍",
    "setNameEn": "Tobi-Kadachi",
    "part": "arms",
    "defense": 182,
    "skills": [
      {
        "skillId": "evade-extender",
        "level": 1
      },
      {
        "skillId": "artful-dodger",
        "level": 1
      }
    ],
    "driftstoneSlots": 1,
    "image": "/images/armor/kadachi-arms.webp"
  },
  {
    "id": "viper-kadachi-arms",
    "name": "朱毒腕甲",
    "nameEn": "",
    "setName": "朱毒",
    "setNameEn": "Viper Tobi-Kadachi",
    "part": "arms",
    "defense": 182,
    "skills": [
      {
        "skillId": "burst-peak",
        "level": 1
      },
      {
        "skillId": "follow-up-paralysis",
        "level": 1
      },
      {
        "skillId": "paralysis-attack",
        "level": 1
      }
    ],
    "driftstoneSlots": 1,
    "image": "/images/armor/viper-kadachi-arms.webp"
  },
  {
    "id": "paolumu-arms",
    "name": "浮空龍腕甲",
    "nameEn": "",
    "setName": "浮空龍",
    "setNameEn": "Paolumu",
    "part": "arms",
    "defense": 182,
    "skills": [
      {
        "skillId": "sp-meter-boost",
        "level": 1
      },
      {
        "skillId": "divine-blessing",
        "level": 1
      }
    ],
    "driftstoneSlots": 1,
    "image": "/images/armor/paolumu-arms.webp"
  },
  {
    "id": "nightshade-paolumu-arms",
    "name": "浮夢腕甲",
    "nameEn": "",
    "setName": "浮夢",
    "setNameEn": "Nightshade Paolumu",
    "part": "arms",
    "defense": 182,
    "skills": [
      {
        "skillId": "sleep-attack",
        "level": 1
      }
    ],
    "driftstoneSlots": 1,
    "image": "/images/armor/nightshade-paolumu-arms.webp"
  },
  {
    "id": "jyuratodus-arms",
    "name": "泥魚龍腕甲",
    "nameEn": "",
    "setName": "泥魚龍",
    "setNameEn": "Jyuratodus",
    "part": "arms",
    "defense": 182,
    "skills": [
      {
        "skillId": "water-attack",
        "level": 1
      }
    ],
    "driftstoneSlots": 1,
    "image": "/images/armor/jyuratodus-arms.webp"
  },
  {
    "id": "anjanath-arms",
    "name": "蠻顎龍腕甲",
    "nameEn": "",
    "setName": "蠻顎龍",
    "setNameEn": "Anjanath",
    "part": "arms",
    "defense": 182,
    "skills": [
      {
        "skillId": "fire-attack",
        "level": 1
      }
    ],
    "driftstoneSlots": 1,
    "image": "/images/armor/anjanath-arms.webp"
  },
  {
    "id": "fulgur-anjanath-arms",
    "name": "雷顎腕甲",
    "nameEn": "",
    "setName": "雷顎",
    "setNameEn": "Fulgur Anjanath",
    "part": "arms",
    "defense": 182,
    "skills": [
      {
        "skillId": "hi-thunder",
        "level": 1
      }
    ],
    "driftstoneSlots": 1,
    "image": "/images/armor/fulgur-anjanath-arms.webp"
  },
  {
    "id": "rathian-arms",
    "name": "雌火龍腕甲",
    "nameEn": "",
    "setName": "雌火龍",
    "setNameEn": "Rathian",
    "part": "arms",
    "defense": 182,
    "skills": [
      {
        "skillId": "lock-on",
        "level": 1
      },
      {
        "skillId": "burst",
        "level": 1
      }
    ],
    "driftstoneSlots": 1,
    "image": "/images/armor/rathian-arms.webp"
  },
  {
    "id": "pink-rathian-arms",
    "name": "火龍心腕甲",
    "nameEn": "",
    "setName": "火龍心",
    "setNameEn": "Pink Rathian",
    "part": "arms",
    "defense": 182,
    "skills": [
      {
        "skillId": "windproof",
        "level": 2
      },
      {
        "skillId": "critical-eye",
        "level": 1
      }
    ],
    "driftstoneSlots": 1,
    "image": "/images/armor/pink-rathian-arms.webp"
  },
  {
    "id": "gold-rathian-arms",
    "name": "金黃澄月腕甲",
    "nameEn": "",
    "setName": "金黃澄月",
    "setNameEn": "Gold Rathian",
    "part": "arms",
    "defense": 182,
    "skills": [
      {
        "skillId": "follow-up-poison",
        "level": 1
      }
    ],
    "driftstoneSlots": 1,
    "image": "/images/armor/gold-rathian-arms.webp"
  },
  {
    "id": "legiana-arms",
    "name": "風漂龍腕甲",
    "nameEn": "",
    "setName": "風漂龍",
    "setNameEn": "Legiana",
    "part": "arms",
    "defense": 182,
    "skills": [
      {
        "skillId": "reload-speed",
        "level": 1
      }
    ],
    "driftstoneSlots": 1,
    "image": "/images/armor/legiana-arms.webp"
  },
  {
    "id": "diablos-arms",
    "name": "角龍腕甲",
    "nameEn": "",
    "setName": "角龍",
    "setNameEn": "Diablos",
    "part": "arms",
    "defense": 182,
    "skills": [
      {
        "skillId": "heroics",
        "level": 2
      },
      {
        "skillId": "partbreaker",
        "level": 1
      }
    ],
    "driftstoneSlots": 1,
    "image": "/images/armor/diablos-arms.webp"
  },
  {
    "id": "black-diablos-arms",
    "name": "暴君角龍腕甲",
    "nameEn": "",
    "setName": "暴君角龍",
    "setNameEn": "Black Diablos",
    "part": "arms",
    "defense": 182,
    "skills": [
      {
        "skillId": "resentment",
        "level": 1
      },
      {
        "skillId": "focus",
        "level": 1
      }
    ],
    "driftstoneSlots": 1,
    "image": "/images/armor/black-diablos-arms.webp"
  },
  {
    "id": "rathalos-arms",
    "name": "火龍腕甲",
    "nameEn": "",
    "setName": "火龍",
    "setNameEn": "Rathalos",
    "part": "arms",
    "defense": 182,
    "skills": [
      {
        "skillId": "fire-resistance",
        "level": 1
      },
      {
        "skillId": "attack-boost",
        "level": 1
      }
    ],
    "driftstoneSlots": 2,
    "image": "/images/armor/rathalos-arms.webp"
  },
  {
    "id": "azure-rathalos-arms",
    "name": "火龍魂腕甲",
    "nameEn": "",
    "setName": "火龍魂",
    "setNameEn": "Azure Rathalos",
    "part": "arms",
    "defense": 182,
    "skills": [
      {
        "skillId": "critical-boost",
        "level": 1
      }
    ],
    "driftstoneSlots": 1,
    "image": "/images/armor/azure-rathalos-arms.webp"
  },
  {
    "id": "silver-rathalos-arms",
    "name": "銀白耀日腕甲",
    "nameEn": "",
    "setName": "銀白耀日",
    "setNameEn": "Silver Rathalos",
    "part": "arms",
    "defense": 182,
    "skills": [
      {
        "skillId": "latent-power",
        "level": 2
      }
    ],
    "driftstoneSlots": 1,
    "image": "/images/armor/silver-rathalos-arms.webp"
  },
  {
    "id": "zinogre-arms",
    "name": "雷狼龍腕甲",
    "nameEn": "",
    "setName": "雷狼龍",
    "setNameEn": "Zinogre",
    "part": "arms",
    "defense": 182,
    "skills": [
      {
        "skillId": "thunder-attack",
        "level": 1
      }
    ],
    "driftstoneSlots": 1,
    "image": "/images/armor/zinogre-arms.webp"
  },
  {
    "id": "tzitzi-arms",
    "name": "眩鳥腕甲",
    "nameEn": "",
    "setName": "眩鳥",
    "setNameEn": "Tzitzi-Ya-Ku",
    "part": "arms",
    "defense": 182,
    "skills": [
      {
        "skillId": "status-sneak-attack",
        "level": 1
      }
    ],
    "driftstoneSlots": 1,
    "image": "/images/armor/tzitzi-arms.webp"
  },
  {
    "id": "odogaron-arms",
    "name": "慘爪龍腕甲",
    "nameEn": "",
    "setName": "慘爪龍",
    "setNameEn": "Odogaron",
    "part": "arms",
    "defense": 182,
    "skills": [
      {
        "skillId": "quick-work",
        "level": 1
      },
      {
        "skillId": "bleeding-resistance",
        "level": 1
      }
    ],
    "driftstoneSlots": 1,
    "image": "/images/armor/odogaron-arms.webp"
  },
  {
    "id": "ebony-odogaron-arms",
    "name": "亡爪腕甲",
    "nameEn": "",
    "setName": "亡爪",
    "setNameEn": "Ebony Odogaron",
    "part": "arms",
    "defense": 182,
    "skills": [
      {
        "skillId": "steadfast",
        "level": 1
      }
    ],
    "driftstoneSlots": 1,
    "image": "/images/armor/ebony-odogaron-arms.webp"
  },
  {
    "id": "vangis-arms",
    "name": "恐暴龍腕甲",
    "nameEn": "",
    "setName": "恐暴龍",
    "setNameEn": "Deviljho",
    "part": "arms",
    "defense": 182,
    "skills": [
      {
        "skillId": "peak-performance",
        "level": 1
      },
      {
        "skillId": "dragon-attack",
        "level": 1
      }
    ],
    "driftstoneSlots": 1,
    "image": "/images/armor/vangis-arms.webp"
  },
  {
    "id": "basarios-arms",
    "name": "岩龍腕甲",
    "nameEn": "",
    "setName": "岩龍",
    "setNameEn": "Basarios",
    "part": "arms",
    "defense": 182,
    "skills": [
      {
        "skillId": "recoil-down",
        "level": 1
      }
    ],
    "driftstoneSlots": 1,
    "image": "/images/armor/basarios-arms.webp"
  },
  {
    "id": "khezu-arms",
    "name": "奇怪龍腕甲",
    "nameEn": "",
    "setName": "奇怪龍",
    "setNameEn": "Khezu",
    "part": "arms",
    "defense": 182,
    "skills": [
      {
        "skillId": "special-insurance",
        "level": 1
      },
      {
        "skillId": "fortify",
        "level": 1
      }
    ],
    "driftstoneSlots": 1,
    "image": "/images/armor/khezu-arms.webp"
  },
  {
    "id": "kushala-arms",
    "name": "鋼龍剛強",
    "nameEn": "",
    "setName": "鋼龍",
    "setNameEn": "Kushala Daora",
    "part": "arms",
    "defense": 182,
    "skills": [
      {
        "skillId": "kushala-frostwind",
        "level": 1
      },
      {
        "skillId": "focus",
        "level": 1
      },
      {
        "skillId": "evade-extender",
        "level": 1
      }
    ],
    "driftstoneSlots": 1,
    "image": "/images/armor/kushala-arms.webp"
  },
  {
    "id": "mizutsune-arms",
    "name": "泡狐龍腕甲",
    "nameEn": "",
    "setName": "泡狐龍",
    "setNameEn": "Mizutsune",
    "part": "arms",
    "defense": 182,
    "skills": [
      {
        "skillId": "bubbly-dance",
        "level": 1
      },
      {
        "skillId": "resuscitate",
        "level": 1
      }
    ],
    "driftstoneSlots": 1,
    "image": "/images/armor/mizutsune-arms.webp"
  },
  {
    "id": "kaiser-arms",
    "name": "帝王腕甲",
    "nameEn": "",
    "setName": "帝王",
    "setNameEn": "Teostra",
    "part": "arms",
    "defense": 182,
    "skills": [
      {
        "skillId": "teostra-blastpowder",
        "level": 1
      },
      {
        "skillId": "artillery",
        "level": 1
      },
      {
        "skillId": "guard",
        "level": 1
      }
    ],
    "driftstoneSlots": 1,
    "image": "/images/armor/kaiser-arms.webp"
  },
  {
    "id": "aknosom-arms",
    "name": "傘鳥腕甲",
    "nameEn": "",
    "setName": "傘鳥",
    "setNameEn": "Aknosom",
    "part": "arms",
    "defense": 182,
    "skills": [
      {
        "skillId": "quick-work",
        "level": 1
      },
      {
        "skillId": "power-prolonger",
        "level": 1
      }
    ],
    "driftstoneSlots": 1,
    "image": "/images/armor/aknosom-arms.webp"
  },
  {
    "id": "sinister-arms",
    "name": "禍鎧【臂甲】",
    "nameEn": "",
    "setName": "禍鎧",
    "setNameEn": "Magnamalo",
    "part": "arms",
    "defense": 182,
    "skills": [
      {
        "skillId": "blast-attack",
        "level": 1
      }
    ],
    "driftstoneSlots": 1,
    "image": "/images/armor/sinister-arms.webp"
  },
  {
    "id": "rajang-arms",
    "name": "金色臂甲",
    "nameEn": "",
    "setName": "金色",
    "setNameEn": "Rajang",
    "part": "arms",
    "defense": 182,
    "skills": [
      {
        "skillId": "fighting-spirit",
        "level": 1
      }
    ],
    "driftstoneSlots": 1,
    "image": "/images/armor/rajang-arms.webp"
  },
  {
    "id": "nergigante-arms",
    "name": "戰紋腕甲",
    "nameEn": "",
    "setName": "戰紋",
    "setNameEn": "Nergigante",
    "part": "arms",
    "defense": 182,
    "skills": [
      {
        "skillId": "nergigante-hunger",
        "level": 1
      },
      {
        "skillId": "offensive-guard",
        "level": 1
      },
      {
        "skillId": "guard",
        "level": 1
      }
    ],
    "driftstoneSlots": 1,
    "image": "/images/armor/nergigante-arms.webp"
  },
  {
    "id": "lagombi-arms",
    "name": "白兔獸腕甲",
    "nameEn": "",
    "setName": "白兔獸",
    "setNameEn": "Lagombi",
    "part": "arms",
    "defense": 182,
    "skills": [
      {
        "skillId": "group-hunt-defense",
        "level": 1
      },
      {
        "skillId": "resentment",
        "level": 1
      }
    ],
    "driftstoneSlots": 2,
    "image": "/images/armor/lagombi-arms.webp"
  },
  {
    "id": "volvidon-arms",
    "name": "赤甲獸腕甲",
    "nameEn": "",
    "setName": "赤甲獸",
    "setNameEn": "Volvidon",
    "part": "arms",
    "defense": 182,
    "skills": [
      {
        "skillId": "morph-boost",
        "level": 1
      }
    ],
    "driftstoneSlots": 1,
    "image": "/images/armor/volvidon-arms.webp"
  },
  {
    "id": "somnacanth-arms",
    "name": "人魚龍腕甲",
    "nameEn": "",
    "setName": "人魚龍",
    "setNameEn": "Somnacanth",
    "part": "arms",
    "defense": 182,
    "skills": [
      {
        "skillId": "dodge-load",
        "level": 1
      }
    ],
    "driftstoneSlots": 1,
    "image": "/images/armor/somnacanth-arms.webp"
  },
  {
    "id": "tigrex-arms",
    "name": "轟龍腕甲",
    "nameEn": "",
    "setName": "轟龍",
    "setNameEn": "Tigrex",
    "part": "arms",
    "defense": 182,
    "skills": [
      {
        "skillId": "earplugs",
        "level": 1
      }
    ],
    "driftstoneSlots": 2,
    "image": "/images/armor/tigrex-arms.webp"
  },
  {
    "id": "brute-tigrex-arms",
    "name": "轟吼腕甲",
    "nameEn": "",
    "setName": "轟吼",
    "setNameEn": "Brute Tigrex",
    "part": "arms",
    "defense": 182,
    "skills": [
      {
        "skillId": "attack-boost-peak",
        "level": 1
      },
      {
        "skillId": "reload-speed",
        "level": 1
      },
      {
        "skillId": "recoil-down",
        "level": 1
      }
    ],
    "driftstoneSlots": 1,
    "image": "/images/armor/brute-tigrex-arms.webp"
  },
  {
    "id": "kirin-arms",
    "name": "麒麟長腕甲",
    "nameEn": "",
    "setName": "麒麟",
    "setNameEn": "Kirin",
    "part": "arms",
    "defense": 182,
    "skills": [
      {
        "skillId": "rajang-thunderclap",
        "level": 1
      },
      {
        "skillId": "critical-boost",
        "level": 1
      },
      {
        "skillId": "weakness-exploit",
        "level": 1
      }
    ],
    "driftstoneSlots": 1,
    "image": "/images/armor/kirin-arms.webp"
  },
  {
    "id": "bazelgeuse-arms",
    "name": "爆鱗龍腕甲",
    "nameEn": "",
    "setName": "爆鱗龍",
    "setNameEn": "Bazelgeuse",
    "part": "arms",
    "defense": 182,
    "skills": [
      {
        "skillId": "maximum-might",
        "level": 1
      }
    ],
    "driftstoneSlots": 1,
    "image": "/images/armor/bazelgeuse-arms.webp"
  },
  {
    "id": "chatacabra-arms",
    "name": "纏蛙腕甲",
    "nameEn": "",
    "setName": "纏蛙",
    "setNameEn": "Chatacabra",
    "part": "arms",
    "defense": 182,
    "skills": [
      {
        "skillId": "defense-ready",
        "level": 1
      }
    ],
    "driftstoneSlots": 2,
    "image": "/images/armor/chatacabra-arms.webp"
  },
  {
    "id": "arzuros-arms",
    "name": "青熊獸腕甲",
    "nameEn": "",
    "setName": "青熊獸",
    "setNameEn": "Arzuros",
    "part": "arms",
    "defense": 182,
    "skills": [
      {
        "skillId": "focus",
        "level": 1
      },
      {
        "skillId": "sp-meter-boost",
        "level": 1
      }
    ],
    "driftstoneSlots": 1,
    "image": "/images/armor/arzuros-arms.webp"
  },
  {
    "id": "glavenus-arms",
    "name": "斬龍腕甲",
    "nameEn": "",
    "setName": "斬龍",
    "setNameEn": "Glavenus",
    "part": "arms",
    "defense": 182,
    "skills": [
      {
        "skillId": "weakness-exploit",
        "level": 1
      }
    ],
    "driftstoneSlots": 1,
    "image": "/images/armor/glavenus-arms.webp"
  },
  {
    "id": "chameleos-arms",
    "name": "霞龍劍裝【大袖】",
    "nameEn": "",
    "setName": "霞龍",
    "setNameEn": "Chameleos",
    "part": "arms",
    "defense": 182,
    "skills": [
      {
        "skillId": "chameleos-miasma",
        "level": 1
      },
      {
        "skillId": "valor",
        "level": 1
      }
    ],
    "driftstoneSlots": 1,
    "image": "/images/armor/chameleos-arms.webp"
  },
  {
    "id": "wroggi-arms",
    "name": "毒狗龍腕甲",
    "nameEn": "",
    "setName": "毒狗龍",
    "setNameEn": "Great Wroggi",
    "part": "arms",
    "defense": 182,
    "skills": [
      {
        "skillId": "critical-eye",
        "level": 1
      }
    ],
    "driftstoneSlots": 1,
    "image": "/images/armor/wroggi-arms.webp"
  },
  {
    "id": "bishaten-arms",
    "name": "天狗獸腕甲",
    "nameEn": "",
    "setName": "天狗獸",
    "setNameEn": "Bishaten",
    "part": "arms",
    "defense": 182,
    "skills": [
      {
        "skillId": "slugger",
        "level": 1
      },
      {
        "skillId": "skyward-striker",
        "level": 1
      }
    ],
    "driftstoneSlots": 1,
    "image": "/images/armor/bishaten-arms.webp"
  },
  {
    "id": "beotodus-arms",
    "name": "冰魚龍腕甲",
    "nameEn": "",
    "setName": "冰魚龍",
    "setNameEn": "Beotodus",
    "part": "arms",
    "defense": 182,
    "skills": [
      {
        "skillId": "lock-on",
        "level": 1
      },
      {
        "skillId": "focus",
        "level": 1
      }
    ],
    "driftstoneSlots": 1,
    "image": "/images/armor/beotodus-arms.webp"
  },
  {
    "id": "nargacuga-arms",
    "name": "迅龍腕甲",
    "nameEn": "",
    "setName": "迅龍",
    "setNameEn": "Nargacuga",
    "part": "arms",
    "defense": 182,
    "skills": [
      {
        "skillId": "status-hit-boost",
        "level": 1
      }
    ],
    "driftstoneSlots": 1,
    "image": "/images/armor/nargacuga-arms.webp"
  },
  {
    "id": "namielle-arms",
    "name": "觸角腕甲",
    "nameEn": "",
    "setName": "觸角",
    "setNameEn": "Namielle",
    "part": "arms",
    "defense": 182,
    "skills": [
      {
        "skillId": "namielle-thunderwave",
        "level": 1
      },
      {
        "skillId": "critical-eye",
        "level": 1
      },
      {
        "skillId": "weakness-exploit",
        "level": 1
      }
    ],
    "driftstoneSlots": 1,
    "image": "/images/armor/namielle-arms.webp"
  },
  {
    "id": "garangolm-arms",
    "name": "剛纏獸腕甲",
    "nameEn": "",
    "setName": "剛纏獸",
    "setNameEn": "Garangolm",
    "part": "arms",
    "defense": 182,
    "skills": [
      {
        "skillId": "resolute",
        "level": 1
      }
    ],
    "driftstoneSlots": 1,
    "image": "/images/armor/garangolm-arms.webp"
  },
  {
    "id": "lunagaron-arms",
    "name": "冰狼龍腕甲",
    "nameEn": "",
    "setName": "冰狼龍",
    "setNameEn": "Lunagaron",
    "part": "arms",
    "defense": 182,
    "skills": [
      {
        "skillId": "charge-shockwave-boost",
        "level": 1
      }
    ],
    "driftstoneSlots": 1,
    "image": "/images/armor/lunagaron-arms.webp"
  },
  {
    "id": "espinas-arms",
    "name": "棘龍雙手",
    "nameEn": "",
    "setName": "棘龍",
    "setNameEn": "Espinas",
    "part": "arms",
    "defense": 182,
    "skills": [
      {
        "skillId": "special-partbreaker",
        "level": 1
      },
      {
        "skillId": "lock-on",
        "level": 1
      }
    ],
    "driftstoneSlots": 1,
    "image": "/images/armor/espinas-arms.webp"
  },
  {
    "id": "malzeno-arms",
    "name": "爵銀龍腕甲",
    "nameEn": "",
    "setName": "爵銀龍",
    "setNameEn": "Malzeno",
    "part": "arms",
    "defense": 182,
    "skills": [
      {
        "skillId": "valstrax-bloodspray",
        "level": 1
      },
      {
        "skillId": "bloody-shroud",
        "level": 1
      },
      {
        "skillId": "resuscitate",
        "level": 1
      }
    ],
    "driftstoneSlots": 1,
    "image": "/images/armor/malzeno-arms.webp"
  },
  {
    "id": "quematrice-arms",
    "name": "炎尾龍腕甲",
    "nameEn": "",
    "setName": "炎尾龍",
    "setNameEn": "Quematrice",
    "part": "arms",
    "defense": 182,
    "skills": [
      {
        "skillId": "ammo-saver",
        "level": 1
      },
      {
        "skillId": "recoil-down",
        "level": 1
      }
    ],
    "driftstoneSlots": 1,
    "image": "/images/armor/quematrice-arms.webp"
  },
  {
    "id": "gossharag-arms",
    "name": "雪鬼獸腕甲",
    "nameEn": "",
    "setName": "雪鬼獸",
    "setNameEn": "Gossharag",
    "part": "arms",
    "defense": 182,
    "skills": [
      {
        "skillId": "ice-attack-peak",
        "level": 1
      },
      {
        "skillId": "divine-blessing",
        "level": 1
      }
    ],
    "driftstoneSlots": 2,
    "image": "/images/armor/gossharag-arms.webp"
  },
  {
    "id": "astalos-arms",
    "name": "電龍腕甲",
    "nameEn": "",
    "setName": "電龍",
    "setNameEn": "Astalos",
    "part": "arms",
    "defense": 182,
    "skills": [
      {
        "skillId": "thunder-attack-peak",
        "level": 1
      },
      {
        "skillId": "absolute-evasion-sp",
        "level": 1
      },
      {
        "skillId": "offensive-dodger",
        "level": 1
      }
    ],
    "driftstoneSlots": 1,
    "image": "/images/armor/astalos-arms.webp"
  },
  {
    "id": "almudron-arms",
    "name": "泥翁龍腕甲",
    "nameEn": "",
    "setName": "泥翁龍",
    "setNameEn": "Almudron",
    "part": "arms",
    "defense": 182,
    "skills": [
      {
        "skillId": "ballistics",
        "level": 1
      },
      {
        "skillId": "artful-dodger",
        "level": 1
      }
    ],
    "driftstoneSlots": 2,
    "image": "/images/armor/almudron-arms.webp"
  },
  {
    "id": "seregios-arms",
    "name": "千刃龍腕甲",
    "nameEn": "",
    "setName": "千刃龍",
    "setNameEn": "Seregios",
    "part": "arms",
    "defense": 182,
    "skills": [
      {
        "skillId": "attack-activation",
        "level": 1
      },
      {
        "skillId": "attack-boost",
        "level": 1
      }
    ],
    "driftstoneSlots": 1,
    "image": "/images/armor/seregios-arms.webp"
  },
  {
    "id": "radobaan-arms",
    "name": "骨鎚龍腕甲",
    "nameEn": "",
    "setName": "骨鎚龍",
    "setNameEn": "Radobaan",
    "part": "arms",
    "defense": 182,
    "skills": [
      {
        "skillId": "slugger",
        "level": 1
      },
      {
        "skillId": "sleep-resistance",
        "level": 1
      }
    ],
    "driftstoneSlots": 1,
    "image": "/images/armor/radobaan-arms.webp"
  },
  {
    "id": "banbaro-arms",
    "name": "猛牛龍腕甲",
    "nameEn": "",
    "setName": "猛牛龍",
    "setNameEn": "Banbaro",
    "part": "arms",
    "defense": 182,
    "skills": [
      {
        "skillId": "offensive-guard",
        "level": 1
      },
      {
        "skillId": "tremor-resistance",
        "level": 1
      }
    ],
    "driftstoneSlots": 1,
    "image": "/images/armor/banbaro-arms.webp"
  },
  {
    "id": "barioth-arms",
    "name": "冰牙龍腕甲",
    "nameEn": "",
    "setName": "冰牙龍",
    "setNameEn": "Barioth",
    "part": "arms",
    "defense": 182,
    "skills": [
      {
        "skillId": "ice-attack",
        "level": 1
      }
    ],
    "driftstoneSlots": 1,
    "image": "/images/armor/barioth-arms.webp"
  }
]
